django_task/__init__.py
django_task/admin.py
django_task/app_settings.py
django_task/apps.py
django_task/exceptions.py
django_task/forms.py
django_task/job.py
django_task/models.py
django_task/task_command.py
django_task/urls.py
django_task/utils.py
django_task/views.py
django_task/locale/it/LC_MESSAGES/django.mo
django_task/locale/it/LC_MESSAGES/django.po
django_task/management/commands/delete_all_tasks.py
django_task/management/commands/dump_all_tasks.py
django_task/management/commands/revoke_pending_tasks.py
django_task/static/css/django_task.css
django_task/static/img/django_task/icon-clock.gif
django_task/static/img/django_task/icon-no.gif
django_task/static/img/django_task/icon-question.gif
django_task/static/img/django_task/icon-spinner.gif
django_task/static/img/django_task/icon-spinner.png
django_task/static/img/django_task/icon-yes.gif
django_task/static/js/django_task.js
django_task/templates/django_task/base.html
django_task/templatetags/__init__.py
django_task/templatetags/django_task_tags.py
django_task/tests/__init__.py
django_task/tests/jobs.py
django_task/tests/models.py
django_task/tests/settings.py
django_task/tests/test_task_models.py
django_task-2.1.0.dist-info/licenses/AUTHORS.rst
django_task-2.1.0.dist-info/licenses/LICENSE
django_task-2.1.0.dist-info/METADATA
django_task-2.1.0.dist-info/WHEEL
django_task-2.1.0.dist-info/top_level.txt
django_task-2.1.0.dist-info/RECORD
