Metadata-Version: 2.4
Name: django-task
Version: 2.1.0
Summary: A Django app to run background tasks and inspect task history; based on django-rq
Author-email: Mario Orlandi <morlandi@brainstorm.it>
License: MIT
Project-URL: Homepage, https://github.com/morlandi/django-task
Project-URL: Issues, https://github.com/morlandi/django-task/issues
Keywords: django-task,django,rq,background,tasks
Classifier: Development Status :: 5 - Production/Stable
Classifier: Intended Audience :: Developers
Classifier: License :: OSI Approved :: MIT License
Classifier: Operating System :: OS Independent
Classifier: Programming Language :: Python
Classifier: Programming Language :: Python :: 3
Classifier: Programming Language :: Python :: 3.8
Classifier: Programming Language :: Python :: 3.9
Classifier: Programming Language :: Python :: 3.10
Classifier: Programming Language :: Python :: 3.11
Classifier: Programming Language :: Python :: 3.12
Classifier: Framework :: Django
Requires-Python: >=3.8
License-File: LICENSE
License-File: AUTHORS.rst
Requires-Dist: django-rq>=3
Dynamic: license-file
